openfigi/__init__.py
openfigi/__main__.py
openfigi/openfigi.py
openfigi-0.0.9.dist-info/LICENSE
openfigi-0.0.9.dist-info/METADATA
openfigi-0.0.9.dist-info/WHEEL
openfigi-0.0.9.dist-info/entry_points.txt
openfigi-0.0.9.dist-info/top_level.txt
openfigi-0.0.9.dist-info/RECORD
