Metadata-Version: 2.1
Name: openfigi
Version: 0.0.9
Summary: A simple wrapper for openfigi.com
Home-page: https://github.com/jwergieluk/openfigi
Author: Julian Wergieluk
Author-email: julian@wergieluk.com
License: MIT License        
Platform: UNKNOWN
Classifier: Development Status :: 4 - Beta
Classifier: License :: OSI Approved :: MIT License
Classifier: Programming Language :: Python :: 3
License-File: LICENSE
Requires-Dist: requests
Requires-Dist: click
